{
    "a": 0,
    "again": 1,
    "at": 2,
    "b": 3,
    "bin": 4,
    "blue": 5,
    "by": 6,
    "c": 7,
    "d": 8,
    "e": 9,
    "eight": 10,
    "f": 11,
    "five": 12,
    "four": 13,
    "g": 14,
    "green": 15,
    "h": 16,
    "i": 17,
    "in": 18,
    "j": 19,
    "k": 20,
    "l": 21,
    "lay": 22,
    "m": 23,
    "n": 24,
    "nine": 25,
    "now": 26,
    "o": 27,
    "one": 28,
    "p": 29,
    "place": 30,
    "please": 31,
    "q": 32,
    "r": 33,
    "red": 34,
    "s": 35,
    "set": 36,
    "seven": 37,
    "six": 38,
    "soon": 39,
    "sp": 40,
    "t": 41,
    "three": 42,
    "two": 43,
    "u": 44,
    "v": 45,
    "white": 46,
    "with": 47,
    "x": 48,
    "y": 49,
    "z": 50,
    "zero": 51
}